producteca/__init__.py
producteca/abstract/__init__.py
producteca/abstract/abstract_dataclass.py
producteca/client.py
producteca/config/__init__.py
producteca/config/config.py
producteca/payments/__init__.py
producteca/payments/payments.py
producteca/payments/tests/__init__.py
producteca/payments/tests/test_payments.py
producteca/products/__init__.py
producteca/products/products.py
producteca/products/search_products.py
producteca/products/tests/__init__.py
producteca/products/tests/test_products.py
producteca/products/tests/test_search_products.py
producteca/sales_orders/__init__.py
producteca/sales_orders/sales_orders.py
producteca/sales_orders/search_sale_orders.py
producteca/sales_orders/tests/__init__.py
producteca/sales_orders/tests/search.json
producteca/sales_orders/tests/test_sales_orders.py
producteca/sales_orders/tests/test_search_so.py
producteca/shipments/__init__.py
producteca/shipments/shipment.py
producteca/shipments/tests/__init__.py
producteca/shipments/tests/test_shipment.py
producteca/utils.py
producteca-2.1.3.dist-info/LICENSE
producteca-2.1.3.dist-info/METADATA
producteca-2.1.3.dist-info/WHEEL
producteca-2.1.3.dist-info/entry_points.txt
producteca-2.1.3.dist-info/RECORD
