Metadata-Version: 2.1
Name: producteca
Version: 2.1.3
Summary: 
Author: Chroma Agency, Matias Rivera
Author-email: mrivera@chroma.agency
Requires-Python: >=3.8,<4.0
Classifier: Programming Language :: Python :: 3
Classifier: Programming Language :: Python :: 3.8
Classifier: Programming Language :: Python :: 3.9
Classifier: Programming Language :: Python :: 3.10
Classifier: Programming Language :: Python :: 3.11
Classifier: Programming Language :: Python :: 3.12
Requires-Dist: coverage (>=7.2.0,<8.0.0)
Requires-Dist: pydantic (>=2.7.4,<3.0.0)
Requires-Dist: requests (>=2.32.4,<3.0.0)
Requires-Dist: typing_extensions (>=4.10.0,<5.0.0)
